{
    "Role":{
        "sensitive":false,
        "type":"string",
        "value":"arn:aws:iam::288342028542:role/sirius-ci"
    },
    "Tasks":{
        "sensitive":false,
        "value":{
            "pull-case":{
                "Cluster":"casrec-migration-development",
                "LaunchType":"FARGATE",
                "NetworkConfiguration":{
                    "AwsvpcConfiguration":{
                        "SecurityGroups":[
                            "sg-08936d537018e5086"
                        ],
                        "Subnets":[
                            "subnet-7f49711b","subnet-a07e41d6","subnet-bd98dde5"
                        ]
                    }
                },
                "TaskDefinition":"arn:aws:ecs:eu-west-1:288342028542:task-definition/etl0-development:320"
            },
            "validation":{
                "Cluster":"casrec-migration-development",
                "LaunchType":"FARGATE",
                "NetworkConfiguration":{
                    "AwsvpcConfiguration":{
                        "SecurityGroups":[
                            "sg-08936d537018e5086"
                        ],
                        "Subnets":[
                            "subnet-7f49711b","subnet-a07e41d6","subnet-bd98dde5"
                        ]
                    }
                },
                "TaskDefinition":"arn:aws:ecs:eu-west-1:288342028542:task-definition/etl5-development:315"
            }
        }
    }
}